hpmpy_project/__init__.py
hpmpy_project-0.0.9.dist-info/METADATA
hpmpy_project-0.0.9.dist-info/WHEEL
hpmpy_project-0.0.9.dist-info/LICENSE
hpmpy_project-0.0.9.dist-info/RECORD
