Metadata-Version: 2.1
Name: hpmpy-project
Version: 0.0.9
Summary: Tweaked Hypermodern Python Project Template w/o Typing
Home-page: https://github.com/tZ3ma/hpmpy_project
License: MIT
Keywords: hypermodern,template
Author: Mathias Ammon
Author-email: mathias.ammon@tuhh.de
Requires-Python: >=3.8,<4.0
Classifier: License :: OSI Approved :: MIT License
Classifier: Programming Language :: Python :: 3
Classifier: Programming Language :: Python :: 3.8
Classifier: Programming Language :: Python :: 3.9
Classifier: Programming Language :: Python :: 3.10
Classifier: Programming Language :: Python :: 3.11
Requires-Dist: nox-poetry (>=1.0.2,<2.0.0)
Requires-Dist: requests (>=2.27.1,<3.0.0)
Project-URL: Repository, https://github.com/tZ3ma/hpmpy_project
